pubdiff
