Metadata-Version: 1.0
Name: Pubdiff
Version: 0.0.3
Summary: http://www.pubdiff.com - easy, anonymous, public code diffs
Home-page: http://www.pubdiff.com
Author: John McFarlane
Author-email: john.mcfarlane@rockfloat.com
License: UNKNOWN
Download-URL: http://www.pubdiff.com/downloads/Pubdiff-0.0.3.tar.gz
Platform: UNKNOWN
Classifier: Development Status :: 2 - Pre-Alpha
Classifier: Intended Audience :: Developers
Classifier: License :: OSI Approved :: MIT License
Classifier: Operating System :: OS Independent
Classifier: Programming Language :: Python
Classifier: Topic :: Internet :: WWW/HTTP
Classifier: Topic :: Software Development :: Version Control
